sr.comp.http-1.9.0-py3.11-nspkg.pth
sr/comp/http/__init__.py
sr/comp/http/__main__.py
sr/comp/http/config.py
sr/comp/http/errors.py
sr/comp/http/escaping_formatter.py
sr/comp/http/json_provider.py
sr/comp/http/logging-stdout.ini
sr/comp/http/logging-syslog.ini
sr/comp/http/manager.py
sr/comp/http/query_utils.py
sr/comp/http/server.py
sr/comp/http/update.py
sr.comp.http-1.9.0.dist-info/AUTHORS.rst
sr.comp.http-1.9.0.dist-info/LICENSE
sr.comp.http-1.9.0.dist-info/METADATA
sr.comp.http-1.9.0.dist-info/WHEEL
sr.comp.http-1.9.0.dist-info/entry_points.txt
sr.comp.http-1.9.0.dist-info/namespace_packages.txt
sr.comp.http-1.9.0.dist-info/top_level.txt
sr.comp.http-1.9.0.dist-info/RECORD
