Metadata-Version: 2.1
Name: sr.comp.http
Version: 1.9.0
Summary: HTTP API for Student Robotics Competition Software
Home-page: https://github.com/PeterJCLaw/srcomp-http
Author: Student Robotics Competition Software SIG
Author-email: srobo-devel@googlegroups.com
Project-URL: Documentation, https://srcomp-http.readthedocs.org/
Project-URL: Code, https://github.com/PeterJCLaw/srcomp-http
Project-URL: Issue tracker, https://github.com/PeterJCLaw/srcomp-http/issues
Classifier: Intended Audience :: Developers
Classifier: Intended Audience :: System Administrators
Classifier: License :: OSI Approved :: GNU General Public License v3 (GPLv3)
Classifier: Operating System :: POSIX :: Linux
Classifier: Programming Language :: Python :: 3
Classifier: Programming Language :: Python :: 3.9
Classifier: Programming Language :: Python :: 3.10
Classifier: Programming Language :: Python :: 3.11
Classifier: Programming Language :: Python :: 3.12
Classifier: Programming Language :: Python :: 3 :: Only
Classifier: Topic :: Internet :: WWW/HTTP
Classifier: Topic :: Internet :: WWW/HTTP :: WSGI :: Application
Requires-Python: >=3.9
License-File: LICENSE
License-File: AUTHORS.rst
Requires-Dist: sr.comp<2,>=1.5
Requires-Dist: Flask>=2.2
Requires-Dist: Werkzeug<4,>=2
Requires-Dist: simplejson<4,>=3.6
Requires-Dist: python-dateutil<3,>=2.2
Requires-Dist: typing-extensions<5,>=3.7.4.2
